AUTHORS
LICENSE
MANIFEST.in
setup.py
cmsplugin_mailchimp/__init__.py
cmsplugin_mailchimp/cms_plugins.py
cmsplugin_mailchimp/forms.py
cmsplugin_mailchimp/models.py
cmsplugin_mailchimp/urls.py
cmsplugin_mailchimp/views.py
cmsplugin_mailchimp/locale/hu/LC_MESSAGES/django.mo
cmsplugin_mailchimp/locale/hu/LC_MESSAGES/django.po
cmsplugin_mailchimp/templatetags/__init__.py
cmsplugin_mailchimp/templatetags/chimptags.py
django_cms_mailchimp.egg-info/PKG-INFO
django_cms_mailchimp.egg-info/SOURCES.txt
django_cms_mailchimp.egg-info/dependency_links.txt
django_cms_mailchimp.egg-info/not-zip-safe
django_cms_mailchimp.egg-info/requires.txt
django_cms_mailchimp.egg-info/top_level.txt